sitemap_cfg/__init__.py
sitemap_cfg/apps.py
sitemap_cfg/tests.py
sitemap_cfg/management/commands/mksitemap.py
sitemap_cfg-0.2.0.dist-info/LICENSE
sitemap_cfg-0.2.0.dist-info/WHEEL
sitemap_cfg-0.2.0.dist-info/METADATA
sitemap_cfg-0.2.0.dist-info/RECORD
