Metadata-Version: 2.1
Name: sitemap_cfg
Version: 0.2.0
Summary: Generate sitemaps from configuration
Author-email: rw crowther <rw.crowther@gmail.com>
Requires-Python: >=3.5
Classifier: Operating System :: OS Independent
Classifier: License :: OSI Approved :: BSD License
Classifier: Programming Language :: Python :: 3
Classifier: Framework :: Django
Project-URL: Home, https://github.com/rcrowther/django-sitemapcfg
